{
    "init_progr_len": 9,
    "vars": [
        "s(2)",
        "s(5)",
        "s(4)",
        "in_1",
        "local_0",
        "in_2",
        "in_4",
        "in_3",
        "s(1)",
        "s(0)",
        "s(3)",
        "in_0"
    ],
    "max_sk_sz": 10,
    "src_ws": [
        "in_0",
        "in_1",
        "in_2",
        "in_3",
        "in_4"
    ],
    "tgt_ws": [
        "s(5)"
    ],
    "user_instrs": [
        {
            "id": "i32.sub_0",
            "disasm": "i32.sub",
            "opcode": "6b",
            "inpt_sk": [
                "s(4)",
                "in_4"
            ],
            "outpt_sk": [
                "s(5)"
            ],
            "push": false,
            "commutative": false,
            "storage": false,
            "gas": 1,
            "size": 1
        },
        {
            "id": "call[function_index(0)]_0",
            "disasm": "call[function_index(0)]",
            "opcode": "10",
            "inpt_sk": [
                "in_0",
                "in_1",
                "in_2"
            ],
            "outpt_sk": [
                "s(1)",
                "s(0)"
            ],
            "push": false,
            "commutative": false,
            "storage": true,
            "gas": 1,
            "size": 1
        },
        {
            "id": "call[function_index(1)]_2",
            "disasm": "call[function_index(1)]",
            "opcode": "10",
            "inpt_sk": [
                "s(2)",
                "s(0)",
                "in_3"
            ],
            "outpt_sk": [
                "s(3)"
            ],
            "push": false,
            "commutative": false,
            "storage": true,
            "gas": 1,
            "size": 1
        },
        {
            "id": "i32.load16_s_1",
            "disasm": "i32.load16_s",
            "opcode": "2e",
            "inpt_sk": [
                "s(1)"
            ],
            "outpt_sk": [
                "s(2)"
            ],
            "push": false,
            "commutative": false,
            "storage": false,
            "gas": 1,
            "size": 1
        },
        {
            "id": "i32.load16_u_3",
            "disasm": "i32.load16_u",
            "opcode": "2f",
            "inpt_sk": [
                "s(3)"
            ],
            "outpt_sk": [
                "s(4)"
            ],
            "push": false,
            "commutative": false,
            "storage": false,
            "gas": 1,
            "size": 1
        }
    ],
    "dependencies": [
        [
            "call[function_index(0)]_0",
            "i32.load16_s_1"
        ],
        [
            "i32.load16_s_1",
            "call[function_index(1)]_2"
        ],
        [
            "call[function_index(1)]_2",
            "i32.load16_u_3"
        ]
    ],
    "original_instrs": "call[function_index(0)] i32.load16_s[5,5] call[function_index(1)] i32.load16_u[5,0] local.tee[local_index(0)] local.get[local_index(1)] local.set[local_index(1)] local.tee[local_index(0)] i32.sub",
    "max_registers_sz": 4,
    "register_changes": [
        [
            "local_0",
            "s(4)"
        ]
    ],
    "rules": "",
    "block": "folder9_json_29",
    "immediate_dependencies": [
        [
            "i32.load16_u_3",
            "i32.sub_0"
        ]
    ],
    "non_immediate_dependencies": [
        [
            "call[function_index(0)]_0",
            "call[function_index(1)]_2"
        ],
        [
            "call[function_index(0)]_0",
            "i32.load16_s_1"
        ],
        [
            "call[function_index(1)]_2",
            "i32.load16_u_3"
        ],
        [
            "i32.load16_s_1",
            "call[function_index(1)]_2"
        ]
    ]
}