{
    "init_progr_len": 11,
    "vars": [
        "s(2)",
        "in_1",
        "local_0",
        "local_1",
        "in_6",
        "in_2",
        "in_4",
        "in_3",
        "s(1)",
        "in_5",
        "in_0"
    ],
    "max_sk_sz": 12,
    "src_ws": [
        "in_0",
        "in_1",
        "in_2",
        "in_3",
        "in_4",
        "in_5",
        "in_6"
    ],
    "tgt_ws": [],
    "user_instrs": [
        {
            "id": "i32.const_0",
            "disasm": "i32.const",
            "opcode": "41",
            "inpt_sk": [],
            "outpt_sk": [
                "s(2)"
            ],
            "push": true,
            "commutative": false,
            "storage": false,
            "value": 7,
            "gas": 1,
            "size": 1
        },
        {
            "id": "i32.load_5",
            "disasm": "i32.load",
            "opcode": "28",
            "inpt_sk": [
                "s(2)"
            ],
            "outpt_sk": [
                "s(1)"
            ],
            "push": false,
            "commutative": false,
            "storage": false,
            "gas": 1,
            "size": 1
        },
        {
            "id": "i32.store8_10",
            "disasm": "i32.store8",
            "opcode": "3a",
            "inpt_sk": [
                "in_5",
                "in_6"
            ],
            "outpt_sk": [],
            "push": false,
            "commutative": false,
            "storage": true,
            "gas": 1,
            "size": 1
        }
    ],
    "dependencies": [
        [
            "i32.load_5",
            "i32.store8_10"
        ]
    ],
    "original_instrs": "local.set[local_index(0)] local.get[local_index(0)] i32.sub local.set[local_index(1)] i32.const[7] i32.load[0,1] local.set[local_index(0)] local.set[local_index(1)] local.set[local_index(1)] local.set[local_index(0)] i32.store8[3,1]",
    "max_registers_sz": 5,
    "register_changes": [
        [
            "local_0",
            "in_4"
        ],
        [
            "local_1",
            "in_3"
        ]
    ],
    "rules": "",
    "block": "folder11_json_23",
    "immediate_dependencies": [
        [
            "i32.const_0",
            "i32.load_5"
        ]
    ],
    "non_immediate_dependencies": []
}