{
    "init_progr_len": 5,
    "vars": [
        "in_1",
        "local_0",
        "local_1",
        "s(0)",
        "in_0"
    ],
    "max_sk_sz": 7,
    "src_ws": [
        "in_0",
        "in_1"
    ],
    "tgt_ws": [
        "s(0)"
    ],
    "user_instrs": [
        {
            "id": "i32.add_0",
            "disasm": "i32.add",
            "opcode": "6a",
            "inpt_sk": [
                "in_0",
                "in_1"
            ],
            "outpt_sk": [
                "s(0)"
            ],
            "push": false,
            "commutative": true,
            "storage": false,
            "gas": 1,
            "size": 1
        }
    ],
    "dependencies": [],
    "original_instrs": "local.tee[local_index(0)] local.tee[local_index(0)] local.set[local_index(1)] local.get[local_index(0)] i32.add",
    "max_registers_sz": 5,
    "register_changes": [
        [
            "local_0",
            "in_0"
        ],
        [
            "local_1",
            "in_0"
        ]
    ],
    "rules": "",
    "original_instrs_with_ids": [
        "LTEE_0",
        "LTEE_0",
        "LSET_1",
        "LGET_0",
        "i32.add_0"
    ],
    "block": "folder5_json_23",
    "immediate_dependencies": [],
    "non_immediate_dependencies": []
}